XStatic_autosize-1.17.2.1-py3.13-nspkg.pth
xstatic/pkg/autosize/__init__.py
xstatic/pkg/autosize/data/jquery.autosize-min.js
xstatic/pkg/autosize/data/jquery.autosize.js
xstatic_autosize-1.17.2.1.dist-info/METADATA
xstatic_autosize-1.17.2.1.dist-info/WHEEL
xstatic_autosize-1.17.2.1.dist-info/namespace_packages.txt
xstatic_autosize-1.17.2.1.dist-info/top_level.txt
xstatic_autosize-1.17.2.1.dist-info/RECORD
