Metadata-Version: 2.4
Name: XStatic-autosize
Version: 1.17.2.1
Summary: autosize 1.17.2 (XStatic packaging standard)
Home-page: http://www.jacklmoore.com/autosize/
Maintainer: Thomas Waldmann
Maintainer-email: tw@waldmann-edv.de
License: (same as autosize)
Keywords: autosize xstatic
Platform: any
Dynamic: description
Dynamic: home-page
Dynamic: keywords
Dynamic: license
Dynamic: maintainer
Dynamic: maintainer-email
Dynamic: platform
Dynamic: summary
